workflow_sandbox/__init__.py
workflow_sandbox-0.5.0.dist-info/LICENSE
workflow_sandbox-0.5.0.dist-info/METADATA
workflow_sandbox-0.5.0.dist-info/WHEEL
workflow_sandbox-0.5.0.dist-info/top_level.txt
workflow_sandbox-0.5.0.dist-info/RECORD
