Metadata-Version: 2.1
Name: workflow-sandbox
Version: 0.5.0
Summary: Testing GitHub actions, Cirrus CI, documentation, and publishing releases of Python packages.
Home-page: https://github.com/rpanderson/workflow-sandbox
License: BSD 3-Clause License
Project-URL: Source Code, https://github.com/rpanderson/workflow-sandbox
Project-URL: Download, https://github.com/rpanderson/workflow-sandbox/releases
Project-URL: Tracker, https://github.com/rpanderson/workflow-sandbox/issues
Keywords: example workflow
Platform: UNKNOWN
Classifier: License :: OSI Approved :: BSD License
Classifier: Programming Language :: Python :: 3 :: Only
Classifier: Programming Language :: Python :: 3.6
Classifier: Programming Language :: Python :: 3.7
Classifier: Programming Language :: Python :: 3.8
Classifier: Topic :: Software Development :: Testing
Classifier: Topic :: Software Development :: Version Control :: Git
Classifier: Topic :: System :: Archiving :: Packaging
Requires-Python: >=3.6
Requires-Dist: setuptools
Requires-Dist: importlib-metadata (>=1.0) ; python_version < "3.8"
Requires-Dist: pywin32 (>=227) ; sys_platform == "win32"
Provides-Extra: development
Requires-Dist: pre-commit (>=2.3.0) ; extra == 'development'
Requires-Dist: black (==19.10b0) ; extra == 'development'
Requires-Dist: flake8 (==3.7.9) ; extra == 'development'
Provides-Extra: docs
Requires-Dist: Sphinx (==3.0.1) ; extra == 'docs'
Requires-Dist: sphinx-rtd-theme (==0.4.3) ; extra == 'docs'
Requires-Dist: recommonmark (==0.6.0) ; extra == 'docs'
Provides-Extra: testing
Requires-Dist: pytest ; extra == 'testing'
